raveberry/VERSION
raveberry/__init__.py
raveberry/manage.py
raveberry/config/cava.config
raveberry/config/raveberry.yaml
raveberry/core/__init__.py
raveberry/core/admin.py
raveberry/core/api.py
raveberry/core/apps.py
raveberry/core/base.py
raveberry/core/models.py
raveberry/core/network_info.py
raveberry/core/redis.py
raveberry/core/redis.pyi
raveberry/core/routing.py
raveberry/core/state_handler.py
raveberry/core/tasks.py
raveberry/core/urls.py
raveberry/core/user_manager.py
raveberry/core/util.py
raveberry/core/lights/__init__.py
raveberry/core/lights/controller.py
raveberry/core/lights/device.py
raveberry/core/lights/exceptions.py
raveberry/core/lights/led_programs.py
raveberry/core/lights/leds.py
raveberry/core/lights/lights.py
raveberry/core/lights/programs.py
raveberry/core/lights/ring.py
raveberry/core/lights/screen.py
raveberry/core/lights/screen_programs.py
raveberry/core/lights/strip.py
raveberry/core/lights/wled.py
raveberry/core/lights/worker.py
raveberry/core/management/commands/rendertemplate.py
raveberry/core/management/commands/startcelery.py
raveberry/core/management/commands/syncsongmetadata.py
raveberry/core/migrations/0001_initial.py
raveberry/core/migrations/0002_auto_20190909_1707.py
raveberry/core/migrations/0003_auto_20190912_2219.py
raveberry/core/migrations/0004_archivedplaylist_created.py
raveberry/core/migrations/0005_auto_20190913_1730.py
raveberry/core/migrations/0006_auto_20200129_2252.py
raveberry/core/migrations/0007_remove_playlistentry_song.py
raveberry/core/migrations/0008_auto_20200514_1213.py
raveberry/core/migrations/0009_delete_pad.py
raveberry/core/migrations/0010_tag_active.py
raveberry/core/migrations/0011_auto_20210427_1339.py
raveberry/core/migrations/0012_currentsong_last_paused.py
raveberry/core/migrations/0013_auto_20210711_1105.py
raveberry/core/migrations/0014_auto_20211011_2041.py
raveberry/core/migrations/0015_install_trgm_extension.py
raveberry/core/migrations/0016_auto_20211128_1900.py
raveberry-0.11.5.dist-info/licenses/AUTHORS
raveberry-0.11.5.dist-info/licenses/LICENSE
raveberry-0.11.5.dist-info/METADATA
raveberry-0.11.5.dist-info/WHEEL
raveberry-0.11.5.dist-info/top_level.txt
raveberry-0.11.5.dist-info/RECORD
