Metadata-Version: 2.4
Name: raveberry
Version: 0.11.5
Summary: A multi-user music server with a focus on participation
Home-page: https://github.com/raveberry/raveberry
Author: Jasmin Hacker
Author-email: raveberry@jhacker.de
Classifier: Development Status :: 4 - Beta
Classifier: Framework :: Django
Classifier: License :: OSI Approved :: GNU Lesser General Public License v3 (LGPLv3)
Classifier: Programming Language :: Python :: 3
Requires-Python: >=3.8
License-File: LICENSE
License-File: AUTHORS
Provides-Extra: install
Requires-Dist: ansible==10.*; extra == "install"
Requires-Dist: pyyaml>=5.4; extra == "install"
Requires-Dist: psycopg2>=2.8.0; extra == "install"
Provides-Extra: run
Requires-Dist: cachetools>=4.2.1; extra == "run"
Requires-Dist: celery>=5.1.2; extra == "run"
Requires-Dist: channels==3.*; extra == "run"
Requires-Dist: channels-redis==3.*; extra == "run"
Requires-Dist: cryptography; extra == "run"
Requires-Dist: Django==4.*; extra == "run"
Requires-Dist: django-ipware>=2.1.0; extra == "run"
Requires-Dist: mutagen>=1.42.0; extra == "run"
Requires-Dist: python-dateutil>=2.8.0; extra == "run"
Requires-Dist: pyyaml>=5.4; extra == "run"
Requires-Dist: qrcode>=6.1; extra == "run"
Requires-Dist: raveberry-mopidyapi>=1.0.0; extra == "run"
Requires-Dist: redis>=3.5.3; extra == "run"
Requires-Dist: requests>=2.22.0; extra == "run"
Requires-Dist: yt-dlp>=2021.12.1; extra == "run"
Requires-Dist: ytmusicapi>=1.3.2; extra == "run"
Provides-Extra: screenvis
Requires-Dist: raveberry-visualization>=0.1.0; extra == "screenvis"
Dynamic: author
Dynamic: author-email
Dynamic: classifier
Dynamic: description
Dynamic: description-content-type
Dynamic: home-page
Dynamic: license-file
Dynamic: provides-extra
Dynamic: requires-python
Dynamic: summary
